loc/__main__.py
loc/cli.py
loc/read.py
loc_lines-0.1.2.dist-info/METADATA
loc_lines-0.1.2.dist-info/WHEEL
loc_lines-0.1.2.dist-info/top_level.txt
loc_lines-0.1.2.dist-info/RECORD
