Metadata-Version: 2.1
Name: loc-lines
Version: 0.1.2
Summary: A small CLI tool that will tell you the number of lines that a file or directory has.
Author: PeppersONLY
Project-URL: Homepage, https://github.com/PeppersONLY/loc
Classifier: Programming Language :: Python :: 3
Classifier: Operating System :: OS Independent
Requires-Python: >=3.8
